docker_gadgets/__init__.py
docker_gadgets/exceptions.py
docker_gadgets/gadgets.py
docker_gadgets/helpers.py
docker_gadgets/py.typed
py_docker_gadgets-0.1.3.dist-info/METADATA
py_docker_gadgets-0.1.3.dist-info/WHEEL
py_docker_gadgets-0.1.3.dist-info/RECORD
