Metadata-Version: 2.1
Name: py-docker-gadgets
Version: 0.1.3
Summary: Some convenience tools for managing docker containers in python
Author: Tucker Beck
Author-email: tucker.beck@gmail.com
Requires-Python: >=3.8,<4.0
Classifier: Programming Language :: Python :: 3
Classifier: Programming Language :: Python :: 3.8
Classifier: Programming Language :: Python :: 3.9
Classifier: Programming Language :: Python :: 3.10
Classifier: Programming Language :: Python :: 3.11
Requires-Dist: docker (>=5.0.3)
Requires-Dist: loguru (>=0.6)
Requires-Dist: py-buzz (>=3.0)
